graphics/__init__.py
graphics/core.py
graphics/events.py
graphics/shapes.py
wayne_graphics-1.1.1.dist-info/licenses/LICENCE
wayne_graphics-1.1.1.dist-info/METADATA
wayne_graphics-1.1.1.dist-info/WHEEL
wayne_graphics-1.1.1.dist-info/top_level.txt
wayne_graphics-1.1.1.dist-info/RECORD
